LICENSE.txt
MANIFEST.in
README.txt
setup.py
pcart_import/__init__.py
pcart_import/admin.py
pcart_import/apps.py
pcart_import/forms.py
pcart_import/models.py
pcart_import/tasks.py
pcart_import.egg-info/PKG-INFO
pcart_import.egg-info/SOURCES.txt
pcart_import.egg-info/dependency_links.txt
pcart_import.egg-info/not-zip-safe
pcart_import.egg-info/requires.txt
pcart_import.egg-info/top_level.txt
pcart_import/locale/ru/LC_MESSAGES/django.mo
pcart_import/locale/ru/LC_MESSAGES/django.po
pcart_import/locale/uk/LC_MESSAGES/django.mo
pcart_import/locale/uk/LC_MESSAGES/django.po
pcart_import/migrations/0001_initial.py
pcart_import/migrations/0002_auto_20170807_2327.py
pcart_import/migrations/0003_auto_20170808_1059.py
pcart_import/migrations/0004_auto_20170808_1214.py
pcart_import/migrations/0005_auto_20170808_1248.py
pcart_import/migrations/0006_auto_20170808_1433.py
pcart_import/migrations/0007_auto_20170808_1434.py
pcart_import/migrations/0008_xlsimportprofile_language.py
pcart_import/migrations/0009_ymlimportprofile.py
pcart_import/migrations/0010_auto_20171116_1421.py
pcart_import/migrations/0011_auto_20171116_1424.py
pcart_import/migrations/0012_ymlpricelist.py
pcart_import/migrations/0013_auto_20171117_1042.py
pcart_import/migrations/0014_auto_20171117_1059.py
pcart_import/migrations/0015_auto_20171117_1512.py
pcart_import/migrations/0016_ymlimportproperty.py
pcart_import/migrations/0017_auto_20171124_1300.py
pcart_import/migrations/0018_auto_20171124_1325.py
pcart_import/migrations/0019_auto_20171124_1333.py
pcart_import/migrations/0020_auto_20171124_1610.py
pcart_import/migrations/0021_auto_20171213_1920.py
pcart_import/migrations/0022_auto_20171226_1547.py
pcart_import/migrations/0023_auto_20171229_1215.py
pcart_import/migrations/0024_auto_20171229_1331.py
pcart_import/migrations/__init__.py
pcart_import/templates/admin/pcart_import/xlspricelist/preview.html